nacos_client/__init__.py
nacos_client/client.py
nacos_client/config.py
nacos_client/config_app.py
nacos_client/config_decorator.py
nacos_client/constant.py
nacos_client/discovery.py
nacos_client/entity.py
nacos_client/registry.py
nacos_client/utils.py
dcone_nacos_client-0.1.6.dist-info/METADATA
dcone_nacos_client-0.1.6.dist-info/WHEEL
dcone_nacos_client-0.1.6.dist-info/RECORD
