Metadata-Version: 2.4
Name: dcone-nacos-client
Version: 0.1.6
Summary: 一个功能完整的 Nacos 客户端封装库，提供配置管理、服务注册与发现功能，支持多层级配置优先级、动态配置更新和优雅关闭。
License: MIT
Author: wangkaiay
Author-email: wangkaiay@digitalchina.com
Requires-Python: >=3.10
Classifier: License :: OSI Approved :: MIT License
Classifier: Programming Language :: Python :: 3
Classifier: Programming Language :: Python :: 3.10
Classifier: Programming Language :: Python :: 3.11
Classifier: Programming Language :: Python :: 3.12
Classifier: Programming Language :: Python :: 3.13
Classifier: Programming Language :: Python :: 3.14
Requires-Dist: nacos-sdk-python (>=2.0.9,<3.0.0)
Requires-Dist: pyyaml (>=6.0.3,<7.0.0)
